Metadata-Version: 1.0
Name: chanFilter
Version: 0.0.2
Summary: A filtering tool for 4chan to find relevant threads
Home-page: http://packages.python.org/chanFilter
Author: Jacob Zipper
Author-email: zipper@jacobzipper.com
License: UNKNOWN
Platform: UNKNOWN
